mcp_materialize_agents/mcp_materialize_agents/__init__.py
mcp_materialize_agents/mcp_materialize_agents/config.py
mcp_materialize_agents/mcp_materialize_agents/system_prompt.md
mcp_materialize_agents/mcp_materialize_agents/tools.sql
mcp_materialize_agents-0.3.2.dist-info/METADATA
mcp_materialize_agents-0.3.2.dist-info/WHEEL
mcp_materialize_agents-0.3.2.dist-info/entry_points.txt
mcp_materialize_agents-0.3.2.dist-info/RECORD
