Metadata-Version: 2.4
Name: mcp_materialize_agents
Version: 0.3.2
Summary: Live data layer for agents. Expose canonical business objects as database-consistent, instantly-queryable SQL views via Model Context Protocol
Author-email: Materialize Inc <support@materialize.com>
Keywords: api,database,materialize,mcp
Requires-Python: >=3.10
Requires-Dist: mcp>=1.10.1
Requires-Dist: psycopg-pool>=3.2.6
Requires-Dist: psycopg[binary]>=3.2.6
Requires-Dist: pydantic>=2.0.0
